forge/__init__.py
forge/_config.py
forge/_counter.py
forge/_exceptions.py
forge/_immutable.py
forge/_marker.py
forge/_parameter.py
forge/_signature.py
forge/_utils.py
python_forge-18.5.0.dist-info/METADATA
python_forge-18.5.0.dist-info/RECORD
python_forge-18.5.0.dist-info/WHEEL
python_forge-18.5.0.dist-info/top_level.txt
