Metadata-Version: 2.1
Name: python-forge
Version: 18.5.0
Summary: forge (python) signatures for fun and profit
Home-page: http://github.com/dfee/forge
Author: Devin Fee
Author-email: devin@devinfee.com
License: MIT
Keywords: signatures,parameters,arguments
Platform: UNKNOWN
Classifier: Development Status :: 5 - Production/Stable
Classifier: Intended Audience :: Developers
Classifier: License :: OSI Approved :: MIT License
Classifier: Topic :: Software Development :: Libraries :: Application Frameworks
Classifier: Programming Language :: Python
Classifier: Programming Language :: Python :: 3 :: Only
Classifier: Programming Language :: Python :: 3.5
Classifier: Programming Language :: Python :: 3.6
Classifier: Programming Language :: Python :: 3.7
Classifier: Programming Language :: Python :: Implementation :: CPython
Classifier: Programming Language :: Python :: Implementation :: PyPy
Provides-Extra: dev
Provides-Extra: testing
Provides-Extra: docs
Provides-Extra: dev
Requires-Dist: coverage; extra == 'dev'
Requires-Dist: mypy; extra == 'dev'
Requires-Dist: pylint; extra == 'dev'
Requires-Dist: pytest; extra == 'dev'
Requires-Dist: sphinx; extra == 'dev'
Requires-Dist: sphinx-autodoc-typehints; extra == 'dev'
Requires-Dist: sphinx-paramlinks; extra == 'dev'
Provides-Extra: docs
Requires-Dist: sphinx (>=1.7.4); extra == 'docs'
Requires-Dist: docutils; extra == 'docs'
Requires-Dist: requests; extra == 'docs'
Requires-Dist: sphinx-autodoc-typehints; extra == 'docs'
Requires-Dist: sphinx-paramlinks; extra == 'docs'
Provides-Extra: testing
Requires-Dist: coverage; extra == 'testing'
Requires-Dist: mypy; extra == 'testing'
Requires-Dist: pylint; extra == 'testing'
Requires-Dist: pytest; extra == 'testing'
